pyglog_annek/__init__.py
pyglog_annek/__main__.py
pyglog_annek/api_client.py
pyglog_annek/config.py
pyglog_annek/main.py
pyglog_annek/models.py
pyglog_annek/utils.py
pyglog_annek-0.5.3.dist-info/METADATA
pyglog_annek-0.5.3.dist-info/WHEEL
pyglog_annek-0.5.3.dist-info/entry_points.txt
pyglog_annek-0.5.3.dist-info/RECORD
