Metadata-Version: 2.3
Name: pyglog-annek
Version: 0.5.3
Summary: Graylog CLI
License: MIT
Author: Mike Mackenna
Author-email: mmackenna@unitedfiregroup.com
Requires-Python: >=3.13
Classifier: License :: OSI Approved :: MIT License
Classifier: Programming Language :: Python :: 3
Classifier: Programming Language :: Python :: 3.13
Requires-Dist: pydantic (>=2.11.7,<3.0.0)
Requires-Dist: python-dotenv-vault (>=0.6.4,<0.7.0)
Requires-Dist: pytz (>=2025.2,<2026.0)
Requires-Dist: requests (>=2.32.4,<3.0.0)
Requires-Dist: typer (>=0.16.0,<0.17.0)
